ckan_wit/__init__.py
ckan_wit/src/__init__.py
ckan_wit/src/ckan_opendata_portals_uris.txt
ckan_wit/src/proxies.py
ckan_wit/src/test_wit.py
ckan_wit/src/uris.py
ckan_wit/src/wit_main.py
ckan_wit-0.1.6.dist-info/LICENSE.rst
ckan_wit-0.1.6.dist-info/METADATA
ckan_wit-0.1.6.dist-info/WHEEL
ckan_wit-0.1.6.dist-info/top_level.txt
ckan_wit-0.1.6.dist-info/RECORD
