Metadata-Version: 2.1
Name: ckan-wit
Version: 0.1.6
Summary: A Wrapper Interface Tool (WIT) that verifies, aggregates, and filters metadata infos across CKAN-compatible Open Dataportals
Home-page: https://ckan-wit-documentation.readthedocs.io/en/latest/
Author: EO
Author-email: c.obinna@stud.uni-goettingen.de
License: UNKNOWN
Platform: UNKNOWN
Classifier: Programming Language :: Python :: 3.6
Classifier: License :: OSI Approved :: MIT License
Classifier: Operating System :: OS Independent
Requires-Python: >=3.6
